py_mssso/__init__.py
py_mssso/helper.py
py_mssso-0.0.2.dist-info/LICENSE
py_mssso-0.0.2.dist-info/METADATA
py_mssso-0.0.2.dist-info/WHEEL
py_mssso-0.0.2.dist-info/top_level.txt
py_mssso-0.0.2.dist-info/RECORD
