Metadata-Version: 2.1
Name: py_mssso
Version: 0.0.2
Summary: MS SSO Helper for Python
Author-email: Sungwon Um <shineum@gmail.com>
License: The MIT License (MIT)
Project-URL: Homepage, https://github.com/shineum/py_mssso
Keywords: azure,sso,msal
Classifier: License :: OSI Approved :: MIT License
Classifier: Programming Language :: Python
Classifier: Programming Language :: Python :: 3
Requires-Python: >=3.7
License-File: LICENSE
Requires-Dist: msal>=1.31.0
